src/api/__init__.py
src/api/constants.py
src/api/ingredient.py
src/api/initialise.py
src/api/plan.py
src/api/settings.py
src/api/shopping_list.py
src/api/unit.py
src/api/utils.py
src/api/recipe/__init__.py
src/api/recipe/formats.py
src/api/recipe/recipe.py
src/api/recipe/serializer.py
src/api/recipe/utils.py
src/cli/__init__.py
src/cli/new.py
src/cli/utils.py
src/cli/view.py
src/cli/routines/__init__.py
src/cli/routines/export_recipes.py
src/cli/routines/plan_recipe.py
src/cli/routines/recipe_wizard.py
yes_chef-0.9.6.dist-info/METADATA
yes_chef-0.9.6.dist-info/WHEEL
yes_chef-0.9.6.dist-info/entry_points.txt
yes_chef-0.9.6.dist-info/top_level.txt
yes_chef-0.9.6.dist-info/RECORD
