Metadata-Version: 2.1
Name: yes-chef
Version: 0.9.6
Summary: A command-line tool for managing recipes and making shopping lists.
Author-email: Robin Neville <robin.m.neville@gmail.com>
Maintainer-email: Robin Neville <robin.m.neville@gmail.com>
Project-URL: Repository, https://github.com/binnev/yes-chef
Requires-Python: >=3.10
Requires-Dist: typer >=0.9
Requires-Dist: colorama >=0.4
Requires-Dist: rich >=13.7
Requires-Dist: shellingham >=1.5
Requires-Dist: pydantic >=2.6
Requires-Dist: pydantic-settings >=2.2
Requires-Dist: aiofiles >=23.2
Requires-Dist: inquirer >=3.2
Requires-Dist: pyyaml >=6.0.1
Provides-Extra: dev
Requires-Dist: ruff ; extra == 'dev'
Requires-Dist: pytest ; extra == 'dev'
Requires-Dist: pytest-asyncio ; extra == 'dev'
Requires-Dist: pytest-cov ; extra == 'dev'
Requires-Dist: responses ; extra == 'dev'
Requires-Dist: pyinstaller ; extra == 'dev'
Requires-Dist: commitizen ; extra == 'dev'
Requires-Dist: mkdocs ; extra == 'dev'
Requires-Dist: mkdocstrings[python] ; extra == 'dev'
Requires-Dist: mike ; extra == 'dev'
